pandantic/__init__.py
pandantic/basemodel.py
pandantic/plugins/__init__.py
pandantic/plugins/pandas.py
pandantic/types.py
pandantic/types_pandantic.py
pandantic/validators/__init__.py
pandantic/validators/base.py
pandantic/validators/pandas.py
pandantic-1.0.0.dist-info/LICENSE
pandantic-1.0.0.dist-info/METADATA
pandantic-1.0.0.dist-info/WHEEL
pandantic-1.0.0.dist-info/RECORD
