Metadata-Version: 2.3
Name: pandantic
Version: 1.0.0
Summary: Gone are the days of black-box dataframes in otherwise type-safe code! Pandantic builds off the Pydantic API to enable validation and filtering of the usual dataframe types (i.e., pandas, etc.)
Author: Wessel Huising
Author-email: wessel@plattevorm.nl
Requires-Python: >=3.10,<4.0
Classifier: Programming Language :: Python :: 3
Classifier: Programming Language :: Python :: 3.10
Classifier: Programming Language :: Python :: 3.11
Classifier: Programming Language :: Python :: 3.12
Classifier: Programming Language :: Python :: 3.13
Requires-Dist: multiprocess (>=0.70.15,<0.71.0)
Requires-Dist: pandas (>=2.0.0,<3.0.0)
Requires-Dist: pandas-stubs (>=2.0.3.230814,<3.0.0.0)
Requires-Dist: pydantic (>=2.0.0,<3.0.0)
